objectgraph/__init__.py
objectgraph/_objectgraph.py
objectgraph/py.typed
objectgraph-1.0.3.dist-info/WHEEL
objectgraph-1.0.3.dist-info/METADATA
objectgraph-1.0.3.dist-info/RECORD
