Metadata-Version: 2.1
Name: objectgraph
Version: 1.0.3
Summary: A basic graph library
Home-page: https://objectgraph.readthedocs.io/
License: MIT
Author: Ronald Oussoren
Author-email: ronaldoussoren@mac.com
Requires-Python: >=3.6,<4
Classifier: Intended Audience :: Developers
Classifier: License :: OSI Approved :: MIT License
Classifier: Programming Language :: Python :: 3 :: Only
Classifier: Programming Language :: Python :: 3
Classifier: Programming Language :: Python :: 3.6
Classifier: Programming Language :: Python :: 3.7
Classifier: Programming Language :: Python :: 3.8
Classifier: Programming Language :: Python :: 3.9
Classifier: Programming Language :: Python :: 3.10
Classifier: Topic :: Software Development :: Libraries :: Python Modules
Classifier: Development Status :: 4 - Beta
Requires-Dist: typing_extensions
Project-URL: Documentation, https://objectgraph.readthedocs.io/
Project-URL: Issue Tracker, https://github.com/ronaldoussoren/objectgraph/issues
Project-URL: Source Code, https://github.com/ronaldoussoren/objectgraph/
Project-URL: Supporting, https://blog.ronaldoussoren.net/support/
